aoikurltofile/aoikurltofile_.py
aoikurltofile/__init__.py
aoikurltofile/__main__.py
AoikUrlToFile-0.1.0.dist-info/DESCRIPTION.rst
AoikUrlToFile-0.1.0.dist-info/entry_points.txt
AoikUrlToFile-0.1.0.dist-info/METADATA
AoikUrlToFile-0.1.0.dist-info/metadata.json
AoikUrlToFile-0.1.0.dist-info/RECORD
AoikUrlToFile-0.1.0.dist-info/top_level.txt
AoikUrlToFile-0.1.0.dist-info/WHEEL
