Metadata-Version: 2.0
Name: AoikUrlToFile
Version: 0.1.0
Summary: A command to create Windows ".url" file. And tips on how to use it to save URL in Chrome or Iron's location bar to a ".url" file in one hotkey.
Home-page: https://github.com/AoiKuiyuyou/AoikUrlToFile
Author: Aoi.Kuiyuyou
Author-email: aoi.kuiyuyou@google.com
License: MIT
Keywords: Chrome Iron location bar save Windows url file hotkey
Platform: UNKNOWN
Classifier: Development Status :: 3 - Alpha
Classifier: Environment :: Console
Classifier: Intended Audience :: End Users/Desktop
Classifier: License :: OSI Approved :: MIT License
Classifier: Operating System :: Microsoft :: Windows
Classifier: Programming Language :: Python :: 2
Classifier: Programming Language :: Python :: 2.7
Classifier: Programming Language :: Python :: 3
Classifier: Programming Language :: Python :: 3.2
Classifier: Programming Language :: Python :: 3.3
Classifier: Programming Language :: Python :: 3.4
